staywiselib/__init__.py
staywiselib/pricing.py
staywiselib_shridharan-0.0.1.dist-info/METADATA
staywiselib_shridharan-0.0.1.dist-info/WHEEL
staywiselib_shridharan-0.0.1.dist-info/RECORD
