Metadata-Version: 2.4
Name: staywiselib-shridharan
Version: 0.0.1
Summary: A reusable library for StayWise project with festival, weekend, and long-stay discount logic.
Author-email: Shridharan M <your.email@example.com>
Classifier: License :: OSI Approved :: MIT License
Classifier: Operating System :: OS Independent
Classifier: Programming Language :: Python :: 3
Requires-Python: >=3.7
